CHANGELOG
LICENSE
MANIFEST.in
README.rst
setup.cfg
setup.py
doc/Makefile
doc/make.bat
doc/build/doctrees/PBassign.doctree
doc/build/doctrees/PBclust.doctree
doc/build/doctrees/PBcount.doctree
doc/build/doctrees/PBstat.doctree
doc/build/doctrees/api_cookbook.doctree
doc/build/doctrees/api_reference.doctree
doc/build/doctrees/environment.pickle
doc/build/doctrees/index.doctree
doc/build/doctrees/installation.doctree
doc/build/doctrees/intro_PB.doctree
doc/build/doctrees/maintenance.doctree
doc/build/doctrees/utilization.doctree
doc/build/doctrees/notebooks/Assignement.doctree
doc/build/doctrees/notebooks/Deformability.doctree
doc/build/doctrees/notebooks/WritePB.doctree
doc/build/doctrees/pages/PB.doctree
doc/build/doctrees/pages/analysis.doctree
doc/build/doctrees/pages/assign.doctree
doc/build/doctrees/pages/demo.doctree
doc/build/doctrees/pages/io.doctree
doc/build/doctrees/pages/pbxplore.doctree
doc/build/doctrees/pages/structure.doctree
doc/build/html/.buildinfo
doc/build/html/PBassign.html
doc/build/html/PBclust.html
doc/build/html/PBcount.html
doc/build/html/PBstat.html
doc/build/html/api_cookbook.html
doc/build/html/api_reference.html
doc/build/html/genindex.html
doc/build/html/index.html
doc/build/html/installation.html
doc/build/html/intro_PB.html
doc/build/html/maintenance.html
doc/build/html/objects.inv
doc/build/html/py-modindex.html
doc/build/html/search.html
doc/build/html/searchindex.js
doc/build/html/utilization.html
doc/build/html/_images/1AY7_B.jpg
doc/build/html/_images/Neq.jpg
doc/build/html/_images/PBs.jpg
doc/build/html/_images/psi_md_traj_all.PB.Neq.jpg
doc/build/html/_images/psi_md_traj_all.PB.logo.jpg
doc/build/html/_images/psi_md_traj_all.PB.map.jpg
doc/build/html/_images/psi_md_traj_all_frame.PB.Neq.15-42.jpg
doc/build/html/_images/psi_md_traj_all_frame.PB.logo.15-42.jpg
doc/build/html/_images/psi_md_traj_all_frame.PB.map.15-42.jpg
doc/build/html/_modules/index.html
doc/build/html/_modules/pbxplore/PB.html
pbxplore.egg-info/PKG-INFO
pbxplore.egg-info/SOURCES.txt
pbxplore.egg-info/dependency_links.txt
pbxplore.egg-info/entry_points.txt
pbxplore.egg-info/pbr.json
pbxplore.egg-info/requires.txt
pbxplore.egg-info/top_level.txt
