Metadata-Version: 2.1
Name: pbxplore
Version: 1.4.0
Summary: PBxplore is a suite of tools dedicated to Protein Block analysis.
Home-page: https://github.com/pierrepo/PBxplore
Author: Pierre Poulain
Author-email: pierre.poulain@cupnet.net
License: MIT
Platform: UNKNOWN
Classifier: Development Status :: 4 - Beta
Classifier: Intended Audience :: Science/Research
Classifier: Intended Audience :: Developers
Classifier: Topic :: Scientific/Engineering :: Bio-Informatics
Classifier: Topic :: Scientific/Engineering :: Chemistry
Classifier: Topic :: Scientific/Engineering :: Physics
Classifier: License :: OSI Approved :: MIT License
Classifier: Programming Language :: Python :: 3.6
Classifier: Programming Language :: Python :: 3.7
Classifier: Programming Language :: Python :: 3.8
Requires-Python: >=3.6
Provides-Extra: analysis
Provides-Extra: all
